Workbook

Sheet Assumptions
A1: US State Expansion — Model Assumptions
A3: Assumption | B3: Value
A4: Weight: Market Size (population) | B4: 0.2
A5: Weight: Population Growth | B5: 0.2
A6: Weight: Median Income | B6: 0.15
A7: Weight: Low Competition | B7: 0.2
A8: Weight: Low Cost (rent+buildout) | B8: 0.15
A9: Weight: Low Unemployment | B9: 0.1
A10: Assumed Operating Margin | B10: 0.14
A12: Note: weights above are the editable levers. Change B4:B9 and the
A13: Ranked Model sheet recalculates the opportunity score automatically.

Sheet Raw Data
A1: State | B1: Population 2025 Millions | C1: Median Household Income | D1: Population Growth 5Yr Pct | E1: Unemployment Rate Pct | F1: Urbanization Pct | G1: Competitor Store Count | H1: Avg Competitor Rating | I1: Avg Competitor Price Index | J1: Avg Commercial Rent Per Sqft | K1: Avg Buildout Cost
A2: Alabama | B2: 28.35 | C2: 88757 | D2: 2.85 | E2: 4.99 | F2: 70.4 | G2: 107 | H2: 4.64 | I2: 0.98 | J2: 23.26 | K2: 354088
A3: Arizona | B3: 4.08 | C3: 74531 | D3: 5.77 | E3: 6.23 | F3: 50.2 | G3: 32 | H3: 3.53 | I3: 0.93 | J3: 12.55 | K3: 313121
A4: Arkansas | B4: 8.37 | C4: 85065 | D4: 2.82 | E4: 5.94 | F4: 86.4 | G4: 66 | H4: 3.26 | I4: 1.14 | J4: 33.78 | K4: 362479
A5: Colorado | B5: 29.52 | C5: 71939 | D5: 8.72 | E5: 5.95 | F5: 87.1 | G5: 66 | H5: 4.61 | I5: 1.19 | J5: 33.29 | K5: 292893
A6: Florida | B6: 2.83 | C6: 88994 | D6: 8.45 | E6: 5.43 | F6: 57 | G6: 61 | H6: 3.21 | I6: 0.87 | J6: 13.35 | K6: 327443
A7: Georgia | B7: 29.25 | C7: 62541 | D7: 3.25 | E7: 5.72 | F7: 46.9 | G7: 10 | H7: 3.97 | I7: 0.95 | J7: 31.5 | K7: 388443
A8: Idaho | B8: 1.96 | C8: 53675 | D8: 4.5 | E8: 4.22 | F8: 73.1 | G8: 5 | H8: 3.65 | I8: 1.04 | J8: 40.95 | K8: 353714
A9: Indiana | B9: 14.34 | C9: 91573 | D9: 6.89 | E9: 5.27 | F9: 51.5 | G9: 96 | H9: 3.75 | I9: 0.93 | J9: 42.91 | K9: 372506
A10: Kansas | B10: 8.08 | C10: 48161 | D10: 4.13 | E10: 6.4 | F10: 77.7 | G10: 31 | H10: 3.63 | I10: 0.88 | J10: 20.51 | K10: 195151
A11: Kentucky | B11: 17.55 | C11: 57692 | D11: 1.15 | E11: 3.82 | F11: 54.5 | G11: 66 | H11: 3.58 | I11: 1.07 | J11: 15.74 | K11: 187400
A12: Missouri | B12: 1.88 | C12: 61417 | D12: 2.59 | E12: 5.26 | F12: 73.4 | G12: 93 | H12: 4.66 | I12: 1.1 | J12: 16.54 | K12: 383766
A13: Nevada | B13: 26.01 | C13: 49021 | D13: 6.63 | E13: 3.15 | F13: 71.5 | G13: 66 | H13: 3.98 | I13: 1.09 | J13: 34.8 | K13: 297796
... A21: Utah | B21: 20.89 | C21: 59653 | D21: 11.55 | E21: 4.17 | F21: 77.7 | G21: 79 | H21: 4.25 | I21: 1.12 | J21: 24.76 | K21: 209855

Sheet Ranked Model
A1: State | B1: Population (mm) | C1: Pop Growth % | D1: Median Income | E1: Unemployment % | F1: Competitor Stores | G1: Rent/SqFt | H1: Buildout Cost | I1: Score: Size | J1: Score: Growth | K1: Score: Income | L1: Score: Low Comp | M1: Score: Low Cost | N1: Score: Low Unemp | O1: Opportunity Score | P1: Predicted Revenue/Store | Q1: Est. Annual Profit/Store | R1: Payback (Years) | S1: Cost Index (helper)
A2: ='Raw Data'!A2 | B2: ='Raw Data'!B2 | C2: ='Raw Data'!D2 | D2: ='Raw Data'!C2 | E2: ='Raw Data'!E2 | F2: ='Raw Data'!G2 | G2: ='Raw Data'!J2 | H2: ='Raw Data'!K2 | I2: =(B2-MIN(B$2:B$21))/(MAX(B$2:B$21)-MIN(B$2:B$21)) | J2: =(C2-MIN(C$2:C$21))/(MAX(C$2:C$21)-MIN(C$2:C$21)) | K2: =(D2-MIN(D$2:D$21))/(MAX(D$2:D$21)-MIN(D$2:D$21)) | L2: =1-(F2-MIN(F$2:F$21))/(MAX(F$2:F$21)-MIN(F$2:F$21)) | M2: =1-(S2-MIN(S$2:S$21))/(MAX(S$2:S$21)-MIN(S$2:S$21)) | N2: =1-(E2-MIN(E$2:E$21))/(MAX(E$2:E$21)-MIN(E$2:E$21)) | O2: =(I2*Assumptions!$B$4+J2*Assumptions!$B$5+K2*Assumptions!$B$6+L2*Assumptions!$B$7+M2*Assumptions!$B$8+N2*Assumptions!$B$9)*100 | P2: =800000+(B2*15000)+(C2*8000)+(D2*6)-(F2*900) | Q2: =P2*Assumptions!$B$10 | R2: =H2/Q2 | S2: =G2+H2/1000
A3: ='Raw Data'!A3 | B3: ='Raw Data'!B3 | C3: ='Raw Data'!D3 | D3: ='Raw Data'!C3 | E3: ='Raw Data'!E3 | F3: ='Raw Data'!G3 | G3: ='Raw Data'!J3 | H3: ='Raw Data'!K3 | I3: =(B3-MIN(B$2:B$21))/(MAX(B$2:B$21)-MIN(B$2:B$21)) | J3: =(C3-MIN(C$2:C$21))/(MAX(C$2:C$21)-MIN(C$2:C$21)) | K3: =(D3-MIN(D$2:D$21))/(MAX(D$2:D$21)-MIN(D$2:D$21)) | L3: =1-(F3-MIN(F$2:F$21))/(MAX(F$2:F$21)-MIN(F$2:F$21)) | M3: =1-(S3-MIN(S$2:S$21))/(MAX(S$2:S$21)-MIN(S$2:S$21)) | N3: =1-(E3-MIN(E$2:E$21))/(MAX(E$2:E$21)-MIN(E$2:E$21)) | O3: =(I3*Assumptions!$B$4+J3*Assumptions!$B$5+K3*Assumptions!$B$6+L3*Assumptions!$B$7+M3*Assumptions!$B$8+N3*Assumptions!$B$9)*100 | P3: =800000+(B3*15000)+(C3*8000)+(D3*6)-(F3*900) | Q3: =P3*Assumptions!$B$10 | R3: =H3/Q3 | S3: =G3+H3/1000
A4: ='Raw Data'!A4 | B4: ='Raw Data'!B4 | C4: ='Raw Data'!D4 | D4: ='Raw Data'!C4 | E4: ='Raw Data'!E4 | F4: ='Raw Data'!G4 | G4: ='Raw Data'!J4 | H4: ='Raw Data'!K4 | I4: =(B4-MIN(B$2:B$21))/(MAX(B$2:B$21)-MIN(B$2:B$21)) | J4: =(C4-MIN(C$2:C$21))/(MAX(C$2:C$21)-MIN(C$2:C$21)) | K4: =(D4-MIN(D$2:D$21))/(MAX(D$2:D$21)-MIN(D$2:D$21)) | L4: =1-(F4-MIN(F$2:F$21))/(MAX(F$2:F$21)-MIN(F$2:F$21)) | M4: =1-(S4-MIN(S$2:S$21))/(MAX(S$2:S$21)-MIN(S$2:S$21)) | N4: =1-(E4-MIN(E$2:E$21))/(MAX(E$2:E$21)-MIN(E$2:E$21)) | O4: =(I4*Assumptions!$B$4+J4*Assumptions!$B$5+K4*Assumptions!$B$6+L4*Assumptions!$B$7+M4*Assumptions!$B$8+N4*Assumptions!$B$9)*100 | P4: =800000+(B4*15000)+(C4*8000)+(D4*6)-(F4*900) | Q4: =P4*Assumptions!$B$10 | R4: =H4/Q4 | S4: =G4+H4/1000
A5: ='Raw Data'!A5 | B5: ='Raw Data'!B5 | C5: ='Raw Data'!D5 | D5: ='Raw Data'!C5 | E5: ='Raw Data'!E5 | F5: ='Raw Data'!G5 | G5: ='Raw Data'!J5 | H5: ='Raw Data'!K5 | I5: =(B5-MIN(B$2:B$21))/(MAX(B$2:B$21)-MIN(B$2:B$21)) | J5: =(C5-MIN(C$2:C$21))/(MAX(C$2:C$21)-MIN(C$2:C$21)) | K5: =(D5-MIN(D$2:D$21))/(MAX(D$2:D$21)-MIN(D$2:D$21)) | L5: =1-(F5-MIN(F$2:F$21))/(MAX(F$2:F$21)-MIN(F$2:F$21)) | M5: =1-(S5-MIN(S$2:S$21))/(MAX(S$2:S$21)-MIN(S$2:S$21)) | N5: =1-(E5-MIN(E$2:E$21))/(MAX(E$2:E$21)-MIN(E$2:E$21)) | O5: =(I5*Assumptions!$B$4+J5*Assumptions!$B$5+K5*Assumptions!$B$6+L5*Assumptions!$B$7+M5*Assumptions!$B$8+N5*Assumptions!$B$9)*100 | P5: =800000+(B5*15000)+(C5*8000)+(D5*6)-(F5*900) | Q5: =P5*Assumptions!$B$10 | R5: =H5/Q5 | S5: =G5+H5/1000
A6: ='Raw Data'!A6 | B6: ='Raw Data'!B6 | C6: ='Raw Data'!D6 | D6: ='Raw Data'!C6 | E6: ='Raw Data'!E6 | F6: ='Raw Data'!G6 | G6: ='Raw Data'!J6 | H6: ='Raw Data'!K6 | I6: =(B6-MIN(B$2:B$21))/(MAX(B$2:B$21)-MIN(B$2:B$21)) | J6: =(C6-MIN(C$2:C$21))/(MAX(C$2:C$21)-MIN(C$2:C$21)) | K6: =(D6-MIN(D$2:D$21))/(MAX(D$2:D$21)-MIN(D$2:D$21)) | L6: =1-(F6-MIN(F$2:F$21))/(MAX(F$2:F$21)-MIN(F$2:F$21)) | M6: =1-(S6-MIN(S$2:S$21))/(MAX(S$2:S$21)-MIN(S$2:S$21)) | N6: =1-(E6-MIN(E$2:E$21))/(MAX(E$2:E$21)-MIN(E$2:E$21)) | O6: =(I6*Assumptions!$B$4+J6*Assumptions!$B$5+K6*Assumptions!$B$6+L6*Assumptions!$B$7+M6*Assumptions!$B$8+N6*Assumptions!$B$9)*100 | P6: =800000+(B6*15000)+(C6*8000)+(D6*6)-(F6*900) | Q6: =P6*Assumptions!$B$10 | R6: =H6/Q6 | S6: =G6+H6/1000
A7: ='Raw Data'!A7 | B7: ='Raw Data'!B7 | C7: ='Raw Data'!D7 | D7: ='Raw Data'!C7 | E7: ='Raw Data'!E7 | F7: ='Raw Data'!G7 | G7: ='Raw Data'!J7 | H7: ='Raw Data'!K7 | I7: =(B7-MIN(B$2:B$21))/(MAX(B$2:B$21)-MIN(B$2:B$21)) | J7: =(C7-MIN(C$2:C$21))/(MAX(C$2:C$21)-MIN(C$2:C$21)) | K7: =(D7-MIN(D$2:D$21))/(MAX(D$2:D$21)-MIN(D$2:D$21)) | L7: =1-(F7-MIN(F$2:F$21))/(MAX(F$2:F$21)-MIN(F$2:F$21)) | M7: =1-(S7-MIN(S$2:S$21))/(MAX(S$2:S$21)-MIN(S$2:S$21)) | N7: =1-(E7-MIN(E$2:E$21))/(MAX(E$2:E$21)-MIN(E$2:E$21)) | O7: =(I7*Assumptions!$B$4+J7*Assumptions!$B$5+K7*Assumptions!$B$6+L7*Assumptions!$B$7+M7*Assumptions!$B$8+N7*Assumptions!$B$9)*100 | P7: =800000+(B7*15000)+(C7*8000)+(D7*6)-(F7*900) | Q7: =P7*Assumptions!$B$10 | R7: =H7/Q7 | S7: =G7+H7/1000
A8: ='Raw Data'!A8 | B8: ='Raw Data'!B8 | C8: ='Raw Data'!D8 | D8: ='Raw Data'!C8 | E8: ='Raw Data'!E8 | F8: ='Raw Data'!G8 | G8: ='Raw Data'!J8 | H8: ='Raw Data'!K8 | I8: =(B8-MIN(B$2:B$21))/(MAX(B$2:B$21)-MIN(B$2:B$21)) | J8: =(C8-MIN(C$2:C$21))/(MAX(C$2:C$21)-MIN(C$2:C$21)) | K8: =(D8-MIN(D$2:D$21))/(MAX(D$2:D$21)-MIN(D$2:D$21)) | L8: =1-(F8-MIN(F$2:F$21))/(MAX(F$2:F$21)-MIN(F$2:F$21)) | M8: =1-(S8-MIN(S$2:S$21))/(MAX(S$2:S$21)-MIN(S$2:S$21)) | N8: =1-(E8-MIN(E$2:E$21))/(MAX(E$2:E$21)-MIN(E$2:E$21)) | O8: =(I8*Assumptions!$B$4+J8*Assumptions!$B$5+K8*Assumptions!$B$6+L8*Assumptions!$B$7+M8*Assumptions!$B$8+N8*Assumptions!$B$9)*100 | P8: =800000+(B8*15000)+(C8*8000)+(D8*6)-(F8*900) | Q8: =P8*Assumptions!$B$10 | R8: =H8/Q8 | S8: =G8+H8/1000
A9: ='Raw Data'!A9 | B9: ='Raw Data'!B9 | C9: ='Raw Data'!D9 | D9: ='Raw Data'!C9 | E9: ='Raw Data'!E9 | F9: ='Raw Data'!G9 | G9: ='Raw Data'!J9 | H9: ='Raw Data'!K9 | I9: =(B9-MIN(B$2:B$21))/(MAX(B$2:B$21)-MIN(B$2:B$21)) | J9: =(C9-MIN(C$2:C$21))/(MAX(C$2:C$21)-MIN(C$2:C$21)) | K9: =(D9-MIN(D$2:D$21))/(MAX(D$2:D$21)-MIN(D$2:D$21)) | L9: =1-(F9-MIN(F$2:F$21))/(MAX(F$2:F$21)-MIN(F$2:F$21)) | M9: =1-(S9-MIN(S$2:S$21))/(MAX(S$2:S$21)-MIN(S$2:S$21)) | N9: =1-(E9-MIN(E$2:E$21))/(MAX(E$2:E$21)-MIN(E$2:E$21)) | O9: =(I9*Assumptions!$B$4+J9*Assumptions!$B$5+K9*Assumptions!$B$6+L9*Assumptions!$B$7+M9*Assumptions!$B$8+N9*Assumptions!$B$9)*100 | P9: =800000+(B9*15000)+(C9*8000)+(D9*6)-(F9*900) | Q9: =P9*Assumptions!$B$10 | R9: =H9/Q9 | S9: =G9+H9/1000
A10: ='Raw Data'!A10 | B10: ='Raw Data'!B10 | C10: ='Raw Data'!D10 | D10: ='Raw Data'!C10 | E10: ='Raw Data'!E10 | F10: ='Raw Data'!G10 | G10: ='Raw Data'!J10 | H10: ='Raw Data'!K10 | I10: =(B10-MIN(B$2:B$21))/(MAX(B$2:B$21)-MIN(B$2:B$21)) | J10: =(C10-MIN(C$2:C$21))/(MAX(C$2:C$21)-MIN(C$2:C$21)) | K10: =(D10-MIN(D$2:D$21))/(MAX(D$2:D$21)-MIN(D$2:D$21)) | L10: =1-(F10-MIN(F$2:F$21))/(MAX(F$2:F$21)-MIN(F$2:F$21)) | M10: =1-(S10-MIN(S$2:S$21))/(MAX(S$2:S$21)-MIN(S$2:S$21)) | N10: =1-(E10-MIN(E$2:E$21))/(MAX(E$2:E$21)-MIN(E$2:E$21)) | O10: =(I10*Assumptions!$B$4+J10*Assumptions!$B$5+K10*Assumptions!$B$6+L10*Assumptions!$B$7+M10*Assumptions!$B$8+N10*Assumptions!$B$9)*100 | P10: =800000+(B10*15000)+(C10*8000)+(D10*6)-(F10*900) | Q10: =P10*Assumptions!$B$10 | R10: =H10/Q10 | S10: =G10+H10/1000
A11: ='Raw Data'!A11 | B11: ='Raw Data'!B11 | C11: ='Raw Data'!D11 | D11: ='Raw Data'!C11 | E11: ='Raw Data'!E11 | F11: ='Raw Data'!G11 | G11: ='Raw Data'!J11 | H11: ='Raw Data'!K11 | I11: =(B11-MIN(B$2:B$21))/(MAX(B$2:B$21)-MIN(B$2:B$21)) | J11: =(C11-MIN(C$2:C$21))/(MAX(C$2:C$21)-MIN(C$2:C$21)) | K11: =(D11-MIN(D$2:D$21))/(MAX(D$2:D$21)-MIN(D$2:D$21)) | L11: =1-(F11-MIN(F$2:F$21))/(MAX(F$2:F$21)-MIN(F$2:F$21)) | M11: =1-(S11-MIN(S$2:S$21))/(MAX(S$2:S$21)-MIN(S$2:S$21)) | N11: =1-(E11-MIN(E$2:E$21))/(MAX(E$2:E$21)-MIN(E$2:E$21)) | O11: =(I11*Assumptions!$B$4+J11*Assumptions!$B$5+K11*Assumptions!$B$6+L11*Assumptions!$B$7+M11*Assumptions!$B$8+N11*Assumptions!$B$9)*100 | P11: =800000+(B11*15000)+(C11*8000)+(D11*6)-(F11*900) | Q11: =P11*Assumptions!$B$10 | R11: =H11/Q11 | S11: =G11+H11/1000
A12: ='Raw Data'!A12 | B12: ='Raw Data'!B12 | C12: ='Raw Data'!D12 | D12: ='Raw Data'!C12 | E12: ='Raw Data'!E12 | F12: ='Raw Data'!G12 | G12: ='Raw Data'!J12 | H12: ='Raw Data'!K12 | I12: =(B12-MIN(B$2:B$21))/(MAX(B$2:B$21)-MIN(B$2:B$21)) | J12: =(C12-MIN(C$2:C$21))/(MAX(C$2:C$21)-MIN(C$2:C$21)) | K12: =(D12-MIN(D$2:D$21))/(MAX(D$2:D$21)-MIN(D$2:D$21)) | L12: =1-(F12-MIN(F$2:F$21))/(MAX(F$2:F$21)-MIN(F$2:F$21)) | M12: =1-(S12-MIN(S$2:S$21))/(MAX(S$2:S$21)-MIN(S$2:S$21)) | N12: =1-(E12-MIN(E$2:E$21))/(MAX(E$2:E$21)-MIN(E$2:E$21)) | O12: =(I12*Assumptions!$B$4+J12*Assumptions!$B$5+K12*Assumptions!$B$6+L12*Assumptions!$B$7+M12*Assumptions!$B$8+N12*Assumptions!$B$9)*100 | P12: =800000+(B12*15000)+(C12*8000)+(D12*6)-(F12*900) | Q12: =P12*Assumptions!$B$10 | R12: =H12/Q12 | S12: =G12+H12/1000
A13: ='Raw Data'!A13 | B13: ='Raw Data'!B13 | C13: ='Raw Data'!D13 | D13: ='Raw Data'!C13 | E13: ='Raw Data'!E13 | F13: ='Raw Data'!G13 | G13: ='Raw Data'!J13 | H13: ='Raw Data'!K13 | I13: =(B13-MIN(B$2:B$21))/(MAX(B$2:B$21)-MIN(B$2:B$21)) | J13: =(C13-MIN(C$2:C$21))/(MAX(C$2:C$21)-MIN(C$2:C$21)) | K13: =(D13-MIN(D$2:D$21))/(MAX(D$2:D$21)-MIN(D$2:D$21)) | L13: =1-(F13-MIN(F$2:F$21))/(MAX(F$2:F$21)-MIN(F$2:F$21)) | M13: =1-(S13-MIN(S$2:S$21))/(MAX(S$2:S$21)-MIN(S$2:S$21)) | N13: =1-(E13-MIN(E$2:E$21))/(MAX(E$2:E$21)-MIN(E$2:E$21)) | O13: =(I13*Assumptions!$B$4+J13*Assumptions!$B$5+K13*Assumptions!$B$6+L13*Assumptions!$B$7+M13*Assumptions!$B$8+N13*Assumptions!$B$9)*100 | P13: =800000+(B13*15000)+(C13*8000)+(D13*6)-(F13*900) | Q13: =P13*Assumptions!$B$10 | R13: =H13/Q13 | S13: =G13+H13/1000
... A21: ='Raw Data'!A21 | B21: ='Raw Data'!B21 | C21: ='Raw Data'!D21 | D21: ='Raw Data'!C21 | E21: ='Raw Data'!E21 | F21: ='Raw Data'!G21 | G21: ='Raw Data'!J21 | H21: ='Raw Data'!K21 | I21: =(B21-MIN(B$2:B$21))/(MAX(B$2:B$21)-MIN(B$2:B$21)) | J21: =(C21-MIN(C$2:C$21))/(MAX(C$2:C$21)-MIN(C$2:C$21)) | K21: =(D21-MIN(D$2:D$21))/(MAX(D$2:D$21)-MIN(D$2:D$21)) | L21: =1-(F21-MIN(F$2:F$21))/(MAX(F$2:F$21)-MIN(F$2:F$21)) | M21: =1-(S21-MIN(S$2:S$21))/(MAX(S$2:S$21)-MIN(S$2:S$21)) | N21: =1-(E21-MIN(E$2:E$21))/(MAX(E$2:E$21)-MIN(E$2:E$21)) | O21: =(I21*Assumptions!$B$4+J21*Assumptions!$B$5+K21*Assumptions!$B$6+L21*Assumptions!$B$7+M21*Assumptions!$B$8+N21*Assumptions!$B$9)*100 | P21: =800000+(B21*15000)+(C21*8000)+(D21*6)-(F21*900) | Q21: =P21*Assumptions!$B$10 | R21: =H21/Q21 | S21: =G21+H21/1000
